Metadata-Version: 2.1
Name: py-my-first-mess-client
Version: 0.1.0
Summary: Messenger Client
Home-page: UNKNOWN
Author: Max
Author-email: gatts@mail.ru
License: UNKNOWN
Platform: UNKNOWN
Requires-Dist: PyQt5
Requires-Dist: sqlalchemy
Requires-Dist: pycryptodome
Requires-Dist: pycryptodomex
